<?xml version="1.0" encoding="utf-8" ?>
<manifest>
  <id>f6c9bf4f-174d-4262-aa42-8e392253e2da-symphony</id>
  <version>1.0.0</version>
  <platform>any</platform>
  <name>Symphony LLC</name>
  <description>Support for viewing and visualization of Symphony log formats: RTC browser log, Spring log (CS, SB), SMB log.</description>	
  <dependency>c0ef79e0-5cbf-42ff-a093-f138c94fe756-chromium</dependency>
  <file type="format">Formats/Symphony - RTC log.format.xml</file>
  <file type="format">Formats/Symphony - SMB log.format.xml</file>
  <file type="format">Formats/Symphony-SpringServiceLog.format.xml</file>
  <file type="entry">logjoint.symphony.plugin.dll</file>
  <file type="dll">logjoint.symphony.plugin.presentation.dll</file>
  <file type="dll">logjoint.symphony.plugin.model.dll</file>
  <file type="dll">Newtonsoft.Json.dll</file>
  <file type="dll">AWSSDK.CloudWatchLogs.dll</file>
  <file type="dll">AWSSDK.Core.dll</file>
  <file type="dll">AWSSDK.SecurityToken.dll</file>
</manifest>